nxselector-3.23.0.data/scripts/nxselector
nxsselector/AddDataSourceDlg.py
nxsselector/CommandThread.py
nxsselector/Data.py
nxsselector/Descriptions.py
nxsselector/Detectors.py
nxsselector/DynamicTools.py
nxsselector/EdDataDlg.py
nxsselector/EdListDlg.py
nxsselector/Element.py
nxsselector/ElementModel.py
nxsselector/Frames.py
nxsselector/GroupsDlg.py
nxsselector/InfoDlg.py
nxsselector/LDataDlg.py
nxsselector/MessageBox.py
nxsselector/OrderDlg.py
nxsselector/Preferences.py
nxsselector/PropertiesDlg.py
nxsselector/Selector.py
nxsselector/ServerState.py
nxsselector/Storage.py
nxsselector/Views.py
nxsselector/__init__.py
nxsselector/qtapi.py
nxsselector/qrc/__init__.py
nxsselector/qrc/resources.rcc
nxsselector/ui/AddDataSourceDlg.ui
nxsselector/ui/EdDataDlg.ui
nxsselector/ui/EdListWg.ui
nxsselector/ui/GroupsDlg.ui
nxsselector/ui/InfoDlg.ui
nxsselector/ui/LDataDlg.ui
nxsselector/ui/OrderDlg.ui
nxsselector/ui/Selector.ui
nxsselector/ui/__init__.py
nxselector-3.23.0.dist-info/METADATA
nxselector-3.23.0.dist-info/WHEEL
nxselector-3.23.0.dist-info/top_level.txt
nxselector-3.23.0.dist-info/RECORD
