Metadata-Version: 2.1
Name: nxselector
Version: 3.23.0
Summary: GUI for Setting Nexus Sardana Recorder
Home-page: https://github.com/nexdatas/nxselector
Author: Jan Kotanski
Author-email: jankotan@gmail.com
Maintainer: Jan Kotanski
Maintainer-email: jankotan@gmail.com
License: GNU GENERAL PUBLIC LICENSE, version 3
Keywords: configuration scan nexus sardana recorder tango component data
Platform: Linux
Platform: Windows
Platform: MacOS 
Classifier: Development Status :: 5 - Production/Stable
Classifier: Intended Audience :: Science/Research
Classifier: Topic :: Scientific/Engineering :: Physics
Classifier: Topic :: Software Development :: Libraries :: Python Modules
Classifier: License :: OSI Approved :: GNU General Public License v2 (GPLv2)
Classifier: Programming Language :: Python :: 2.7
Classifier: Programming Language :: Python :: 3
Classifier: Programming Language :: Python :: 3.5
Classifier: Programming Language :: Python :: 3.6
Classifier: Programming Language :: Python :: 3.7
Classifier: Programming Language :: Python :: 3.8
Classifier: Programming Language :: Python :: 3.9
Classifier: Programming Language :: Python :: 3.10
Classifier: Programming Language :: Python :: 3.11
Classifier: Programming Language :: Python :: 3.12
